{
    "version": "0.1.116",
    "architecture": {
        "32bit": {
            "url": "https://github.com/outblocks/outblocks-cli/releases/download/v0.1.116/outblocks-0.1.116-windows_386.zip",
            "bin": [
                "ok.exe"
            ],
            "hash": "278e7717bf47297d430584ba36305a66e4125e12fc349186fcd86b16f36f9e47"
        },
        "64bit": {
            "url": "https://github.com/outblocks/outblocks-cli/releases/download/v0.1.116/outblocks-0.1.116-windows_amd64.zip",
            "bin": [
                "ok.exe"
            ],
            "hash": "56779150b570a23fb57de761003bcd744b2a02b79b5f3ff25db931068477d75f"
        }
    },
    "homepage": "https://outblocks.io",
    "license": "MIT",
    "description": "Auto devops."
}